admin_log_entries/__init__.py
admin_log_entries/admin.py
admin_log_entries/settings.py
admin_log_entries/templates/admin/admin/logentry/change_list.html
django_adminlogentries-0.1.3.dist-info/METADATA
django_adminlogentries-0.1.3.dist-info/WHEEL
django_adminlogentries-0.1.3.dist-info/licenses/LICENSE.txt
django_adminlogentries-0.1.3.dist-info/RECORD
