Metadata-Version: 2.1
Name: django-adminlogentries
Version: 0.1.3
Summary: A Django app that provides a ModelAdmin for django.contrib.admin's LogEntry model (with everything except the list disabled)
Project-URL: Homepage, https://github.com/ataylor32/django-adminlogentries
Project-URL: Repository, https://github.com/ataylor32/django-adminlogentries.git
Project-URL: Issues, https://github.com/ataylor32/django-adminlogentries/issues
Project-URL: Changelog, https://github.com/ataylor32/django-adminlogentries/blob/master/CHANGELOG.md
Author-email: Adam Taylor <ataylor32@gmail.com>
License-File: LICENSE.txt
Classifier: License :: OSI Approved :: MIT License
Classifier: Operating System :: OS Independent
Classifier: Programming Language :: Python :: 2
Classifier: Programming Language :: Python :: 3
Requires-Dist: django
